PhyExp/__init__.py
PhyExp/dataprocess.py
PhyExp/electricity.py
phyexp-1.1.0.dist-info/licenses/LICENSE
phyexp-1.1.0.dist-info/METADATA
phyexp-1.1.0.dist-info/WHEEL
phyexp-1.1.0.dist-info/top_level.txt
phyexp-1.1.0.dist-info/RECORD
